rifatozvyska.py
rifatozvyska-1.0.0.dist-info/WHEEL
rifatozvyska-1.0.0.dist-info/METADATA
rifatozvyska-1.0.0.dist-info/RECORD
